iewt/__init__.py
iewt/_version.py
iewt/handler.py
iewt/main.py
iewt/policy.py
iewt/settings.py
iewt/utils.py
iewt/worker.py
iewt/static/css/bootstrap.min.css
iewt/static/css/fullscreen.min.css
iewt/static/css/xterm.min.css
iewt/static/css/fonts/.gitignore
iewt/static/img/favicon.png
iewt/static/js/bootstrap.min.js
iewt/static/js/iewt.js
iewt/static/js/jquery.min.js
iewt/static/js/main.js
iewt/static/js/popper.min.js
iewt/static/js/xterm-addon-fit.min.js
iewt/static/js/xterm.min.js
iewt/templates/iewt.html
iewt/templates/index.html
iewt-1.3.4.dist-info/LICENSE
iewt-1.3.4.dist-info/METADATA
iewt-1.3.4.dist-info/WHEEL
iewt-1.3.4.dist-info/entry_points.txt
iewt-1.3.4.dist-info/top_level.txt
iewt-1.3.4.dist-info/RECORD
