Metadata-Version: 2.1
Name: iewt
Version: 1.3.4
Summary: Interactive embedded web terminal
Home-page: https://github.com/TXH2020/iewt
Author: Tejas Hegde
Author-email: 1001.tejas@gmail.com
License: MIT
Platform: UNKNOWN
Classifier: Programming Language :: Python
Classifier: Programming Language :: Python :: 3
Classifier: Programming Language :: Python :: 3.8
Classifier: Programming Language :: Python :: 3.9
Classifier: Programming Language :: Python :: 3.10
Classifier: Programming Language :: Python :: 3.11
Requires-Dist: paramiko >=2.3.1
Requires-Dist: tornado >=4.5.0
